rtl/counter.v
`timescale 1ns/1ps

module counter (
    input clk,
    input rst,
    input en,
    output reg [3:0] q
);

    always @(posedge clk) begin
        if (rst)
            q <= 4'b0;
        else if (en)
            q <= q + 1'b1;
    end

endmodule

tb/counter_tb.v
`timescale 1ns/1ps

module counter_tb;

    reg clk;
    reg rst;
    reg en;
    wire [3:0] q;

    counter dut (
        .clk(clk),
        .rst(rst),
        .en(en),
        .q(q)
    );

    always #5 clk = ~clk;

    initial begin
        $dumpfile("results/counter.vcd");
        $dumpvars(0, counter_tb);

        clk = 0;
        rst = 1;
        en = 0;

        #20;
        rst = 0;
        en = 1;

        #100;
        en = 0;

        #30;
        $finish;
    end

endmodule

results/counter.vcd
$date
	Sun May 24 17:16:08 2026
$end
$version
	Icarus Verilog
$end
$timescale
	1ps
$end
$scope module counter_tb $end
$var wire 4 ! q [3:0] $end
$var reg 1 " clk $end
$var reg 1 # en $end
$var reg 1 $ rst $end
$scope module dut $end
$var wire 1 " clk $end
$var wire 1 # en $end
$var wire 1 $ rst $end
$var reg 4 % q [3:0] $end
$upscope $end
$upscope $end
$enddefinitions $end
$comment Show the parameter values. $end
$dumpall
$end
#0
$dumpvars
bx %
1$
0#
0"
bx !
$end
#5000
b0 !
b0 %
1"
#10000
0"
#15000
1"
#20000
0"
1#
0$
#25000
b1 !
b1 %
1"
#30000
0"
#35000
b10 !
b10 %
1"
#40000
0"
#45000
b11 !
b11 %
1"
#50000
0"
#55000
b100 !
b100 %
1"
#60000
0"
#65000
b101 !
b101 %
1"
#70000
0"
#75000
b110 !
b110 %
1"
#80000
0"
#85000
b111 !
b111 %
1"
#90000
0"
#95000
b1000 !
b1000 %
1"
#100000
0"
#105000
b1001 !
b1001 %
1"
#110000
0"
#115000
b1010 !
b1010 %
1"
#120000
0"
0#
