rtl/scan_dff.v
`timescale 1ns/1ps

module scan_dff (
    input clk,
    input rst,
    input scan_en,
    input d,
    input scan_in,
    output reg q
);

    always @(posedge clk) begin
        if (rst) 
            q <= 1'b0;
        else if (scan_en) 
            q <= scan_in;
        else 
            q <= d;
    end

endmodule

rtl/counter_scan.v
`timescale 1ns/1ps

module counter_scan (
    input clk,
    input rst,
    input en,
    input scan_en,
    input scan_in,
    output scan_out,
    output [3:0] q
);

    wire [3:0] next_q;
    assign next_q = en ? (q + 1'b1) : q;

    scan_dff u_scan_ff0 (
        .clk(clk),
        .rst(rst),
        .scan_en(scan_en),
        .d(next_q[0]),
        .scan_in(scan_in),
        .q(q[0])
    );

    scan_dff u_scan_ff1 (
        .clk(clk),
        .rst(rst),
        .scan_en(scan_en),
        .d(next_q[1]),
        .scan_in(q[0]),
        .q(q[1])
    );

    scan_dff u_scan_ff2 (
        .clk(clk),
        .rst(rst),
        .scan_en(scan_en),
        .d(next_q[2]),
        .scan_in(q[1]),
        .q(q[2])
    );

    scan_dff u_scan_ff3 (
        .clk(clk),
        .rst(rst),
        .scan_en(scan_en),
        .d(next_q[3]),
        .scan_in(q[2]),
        .q(q[3])
    );

    assign scan_out = q[3];

endmodule

tb/counter_scan_tb.v
`timescale 1ns/1ps

module counter_scan_tb;

    reg clk;
    reg rst;
    reg en;
    reg scan_en;
    reg scan_in;

    wire scan_out;
    wire [3:0] q;

    reg [3:0] scanned_data;
    integer i;

    counter_scan dut (
        .clk(clk),
        .rst(rst),
        .en(en),
        .scan_en(scan_en),
        .scan_in(scan_in),
        .scan_out(scan_out),
        .q(q)
    );

    always #5 clk = ~clk;

    task scan_load;
        input [3:0] data;
        
        begin
            scan_en = 1'b1;
            en = 1'b0;

            for (i = 3; i >= 0; i = i - 1) begin
                @(negedge clk);
                scan_in = data[i];
                @(posedge clk);
                #1;
            end
        end
    endtask

    task scan_read;
        begin
            scan_en = 1'b1;
            en = 1'b0;
            scanned_data = 4'b0000;

            for (i = 3; i >= 0; i = i - 1) begin
                @(negedge clk);
                scanned_data[i] = scan_out;
                scan_in = 1'b0;
                @(posedge clk);
                #1;
            end
        end
    endtask

    initial begin
        $dumpfile("results/counter_scan.vcd");
        $dumpvars(0, counter_scan_tb);

        clk = 0;
        rst = 1;
        en = 0;
        scan_en = 0;
        scan_in = 0;

        repeat (2) @(posedge clk);
        rst = 0;

        en = 1;
        scan_en = 0;
        repeat (4) @(posedge clk);
        #1;

        $display("Normal counter mode, q = %b", q);

        scan_load(4'b1010);
        $display("After scan load, q = %b", q);

        if (q !== 4'b1010) begin
            $display("ERROR: Scan load failed.");
            $finish;
        end

        scan_en = 0;
        en = 1;
        @(posedge clk);
        #1;

        $display("After one capture clock, q = %b", q);

        scan_read();
        $display("Scanned out data = %b", scanned_data);

        if (scanned_data !== 4'b1011) begin
            $display("ERROR: Scan read failed.");
            $finish;
        end

        $display("SCAN CHAIN DEMO PASSED.");
        $finish;
    end

endmodule

results/counter_scan.vcd
$date
	Sun May 24 17:16:22 2026
$end
$version
	Icarus Verilog
$end
$timescale
	1ps
$end
$scope module counter_scan_tb $end
$var wire 1 ! scan_out $end
$var wire 4 " q [3:0] $end
$var reg 1 # clk $end
$var reg 1 $ en $end
$var reg 1 % rst $end
$var reg 1 & scan_en $end
$var reg 1 ' scan_in $end
$var reg 4 ( scanned_data [3:0] $end
$var integer 32 ) i [31:0] $end
$scope module dut $end
$var wire 1 # clk $end
$var wire 1 $ en $end
$var wire 1 % rst $end
$var wire 1 & scan_en $end
$var wire 1 ' scan_in $end
$var wire 1 ! scan_out $end
$var wire 4 * q [3:0] $end
$var wire 4 + next_q [3:0] $end
$scope module u_scan_ff0 $end
$var wire 1 # clk $end
$var wire 1 , d $end
$var wire 1 % rst $end
$var wire 1 & scan_en $end
$var wire 1 ' scan_in $end
$var reg 1 - q $end
$upscope $end
$scope module u_scan_ff1 $end
$var wire 1 # clk $end
$var wire 1 . d $end
$var wire 1 % rst $end
$var wire 1 & scan_en $end
$var wire 1 / scan_in $end
$var reg 1 0 q $end
$upscope $end
$scope module u_scan_ff2 $end
$var wire 1 # clk $end
$var wire 1 1 d $end
$var wire 1 % rst $end
$var wire 1 & scan_en $end
$var wire 1 2 scan_in $end
$var reg 1 3 q $end
$upscope $end
$scope module u_scan_ff3 $end
$var wire 1 # clk $end
$var wire 1 4 d $end
$var wire 1 % rst $end
$var wire 1 & scan_en $end
$var wire 1 5 scan_in $end
$var reg 1 6 q $end
$upscope $end
$upscope $end
$scope task scan_load $end
$var reg 4 7 data [3:0] $end
$upscope $end
$scope task scan_read $end
$upscope $end
$upscope $end
$enddefinitions $end
$comment Show the parameter values. $end
$dumpall
$end
#0
$dumpvars
bx 7
x6
x5
x4
x3
x2
x1
x0
x/
x.
x-
x,
bx +
bx *
bx )
bx (
0'
0&
1%
0$
0#
bx "
x!
$end
#5000
0,
0.
01
04
0/
02
05
0!
b0 +
0-
00
03
b0 "
b0 *
06
1#
#10000
0#
#15000
1,
b1 +
1$
0%
1#
#20000
0#
#25000
0,
1.
1/
b10 +
b1 "
b1 *
1-
1#
#30000
0#
#35000
1,
12
0/
b11 +
10
b10 "
b10 *
0-
1#
#40000
0#
#45000
0,
0.
11
1/
b100 +
b11 "
b11 *
1-
1#
#50000
0#
#55000
1,
15
02
0/
b101 +
13
00
b100 "
b100 *
0-
1#
#56000
0,
b100 +
b11 )
0$
1&
b1010 7
#60000
1'
0#
#65000
1,
01
14
1/
05
1!
b1001 +
1-
03
b1001 "
b1001 *
16
1#
#66000
b10 )
#70000
0'
0#
#75000
0,
1.
04
0!
12
0/
b10 +
06
10
b10 "
b10 *
0-
1#
#76000
b1 )
#80000
1'
0#
#85000
1,
0.
11
1/
02
15
b101 +
1-
00
b101 "
b101 *
13
1#
#86000
b0 )
#90000
0'
0#
#95000
0,
1.
01
14
1!
05
12
0/
b1010 +
16
03
10
b1010 "
b1010 *
0-
1#
#96000
1,
b1011 +
1$
0&
b11111111111111111111111111111111 )
#100000
0#
#105000
0,
0.
11
1/
b1100 +
b1011 "
b1011 *
1-
1#
#106000
1,
1.
01
b1011 +
b11 )
b0 (
0$
1&
#110000
b1000 (
0#
#115000
0,
11
04
0!
15
0/
b110 +
06
13
b110 "
b110 *
0-
1#
#116000
b10 )
#120000
0#
#125000
0.
14
02
1!
b1100 +
00
b1100 "
b1100 *
16
1#
#126000
b1 )
#130000
b1010 (
0#
#135000
01
05
b1000 +
b1000 "
b1000 *
03
1#
#136000
b0 )
#140000
b1011 (
0#
#145000
04
0!
b0 +
b0 "
b0 *
06
1#
#146000
b11111111111111111111111111111111 )
